pystyle/__init__.py
pystyle-2.9.dist-info/LICENSE
pystyle-2.9.dist-info/METADATA
pystyle-2.9.dist-info/WHEEL
pystyle-2.9.dist-info/top_level.txt
pystyle-2.9.dist-info/RECORD
