Metadata-Version: 1.0
Name: pystyle
Version: 2.9
Summary: by billythegoat356, loTus01 and BlueRed
Home-page: UNKNOWN
Author: UNKNOWN
Author-email: <billythegoat356@gmail.com>
License: Eclipse Public License 2.0
Keywords: cli,fade,colors,terminal,tui
Platform: UNKNOWN
